{"tasks":[{"environment":{},"displayName":"Publish","alwaysRun":false,"continueOnError":false,"condition":"succeeded()","enabled":true,"timeoutInMinutes":0,"inputs":{"command":"publish","publishWebProjects":"true","projects":"","custom":"","arguments":"--configuration $(BuildConfiguration) --output $(build.artifactstagingdirectory) -r $(PublishRuntime)","restoreArguments":"","publishTestResults":"true","testRunTitle":"","zipAfterPublish":"false","modifyOutputPath":"true","selectOrConfig":"select","feedRestore":"","includeNuGetOrg":"true","nugetConfigPath":"","externalEndpoints":"","noCache":"false","packagesDirectory":"","verbosityRestore":"Detailed","searchPatternPush":"$(Build.ArtifactStagingDirectory)/*.nupkg","nuGetFeedType":"internal","feedPublish":"","publishPackageMetadata":"true","externalEndpoint":"","searchPatternPack":"**/*.csproj","configurationToPack":"$(BuildConfiguration)","outputDir":"$(Build.ArtifactStagingDirectory)","nobuild":"false","includesymbols":"false","includesource":"false","versioningScheme":"off","versionEnvVar":"","requestedMajorVersion":"1","requestedMinorVersion":"0","requestedPatchVersion":"0","buildProperties":"","verbosityPack":"Detailed","workingDirectory":""},"task":{"id":"5541a522-603c-47ad-91fc-a4b1d163081b","versionSpec":"2.*","definitionType":"task"}},{"environment":{},"displayName":"Transoform web.config","alwaysRun":false,"continueOnError":false,"condition":"succeeded()","enabled":true,"timeoutInMinutes":0,"inputs":{"targetType":"filePath","filePath":"./deploy/basic/webconfig-transform.ps1","arguments":"-path $(build.artifactstagingdirectory)/Web/web.config","script":"# Write your PowerShell commands here.\n\nWrite-Host \"Hello World\"\n","errorActionPreference":"stop","failOnStderr":"false","ignoreLASTEXITCODE":"false","pwsh":"false","workingDirectory":""},"task":{"id":"e213ff0f-5d5c-4791-802d-52ea3e7be1f1","versionSpec":"2.*","definitionType":"task"}},{"environment":{},"displayName":"Archive","alwaysRun":false,"continueOnError":false,"condition":"succeeded()","enabled":true,"timeoutInMinutes":0,"inputs":{"rootFolderOrFile":"$(Build.ArtifactStagingDirectory)/Web","includeRootFolder":"false","archiveType":"zip","sevenZipCompression":"5","tarCompression":"gz","archiveFile":"$(Build.ArtifactStagingDirectory)/Web.zip","replaceExistingArchive":"true","verbose":"false","quiet":"false"},"task":{"id":"d8b84976-e99a-4b86-b885-4849694435b0","versionSpec":"2.*","definitionType":"task"}},{"environment":{},"displayName":"Delete","alwaysRun":false,"continueOnError":false,"condition":"succeeded()","enabled":true,"timeoutInMinutes":0,"inputs":{"SourceFolder":"$(Build.ArtifactStagingDirectory)/Web","Contents":"**/*","RemoveSourceFolder":"true"},"task":{"id":"b7e8b412-0437-4065-9371-edc5881de25b","versionSpec":"1.*","definitionType":"task"}},{"environment":{},"displayName":"Publish Artifact","alwaysRun":false,"continueOnError":false,"condition":"succeeded()","enabled":true,"timeoutInMinutes":0,"inputs":{"PathtoPublish":"$(Build.ArtifactStagingDirectory)","ArtifactName":"$(PublishArtifactName)","ArtifactType":"Container","TargetPath":"","Parallel":"false","ParallelCount":"8","FileCopyOptions":""},"task":{"id":"2ff763a7-ce83-4e1f-bc89-0ae63477cebe","versionSpec":"1.*","definitionType":"task"}}],"runsOn":["Agent"],"revision":3,"createdBy":{"displayName":"totsamiynixon","id":"c3c38626-6211-42a1-a5f3-774e7d707ca1","uniqueName":"totsamiynixon@gmail.com"},"createdOn":"2020-09-16T15:18:21.673Z","modifiedBy":{"displayName":"totsamiynixon","id":"c3c38626-6211-42a1-a5f3-774e7d707ca1","uniqueName":"totsamiynixon@gmail.com"},"modifiedOn":"2020-09-17T06:58:26.873Z","comment":"fixed archieve job","id":"ee0d3e88-45c8-4edd-8c0c-8a083d0ecffc","name":"CSM | Publish Artifact","version":{"major":1,"minor":0,"patch":0,"isTest":false},"iconUrl":"/bsac2020/_static/tfs/M174_20200916.1/_content/icon-meta-task.png","friendlyName":"CSM | Publish Artifact","description":"","category":"Deploy","definitionType":"metaTask","author":"totsamiynixon","demands":[],"groups":[],"inputs":[{"aliases":[],"options":{},"properties":{},"name":"BuildConfiguration","label":"BuildConfiguration","defaultValue":"Release","required":true,"type":"string","helpMarkDown":"","groupName":""},{"aliases":[],"options":{},"properties":{},"name":"PublishArtifactName","label":"PublishArtifactName","defaultValue":"ClearSkyMapsSimple-Basic-Staging","required":true,"type":"string","helpMarkDown":"The name of the artifact to create in the publish location.","groupName":""},{"aliases":[],"options":{},"properties":{},"name":"PublishRuntime","label":"PublishRuntime","defaultValue":"win10-x64","required":true,"type":"string","helpMarkDown":"","groupName":""}],"satisfies":[],"sourceDefinitions":[],"dataSourceBindings":[],"instanceNameFormat":"Task group: CSM | Publish Artifact $(BuildConfiguration)","preJobExecution":{},"execution":{},"postJobExecution":{}}